{
  "2": {
    "s": 3,
    "ss": 3,
    "t": 3,
    "c": 4,
    "ie": 0.0,
    "ee": 3.0,
    "e->w3": 2.0
  },
  "4": {
    "s": 2,
    "ss": 2,
    "t": 2,
    "c": 0,
    "ie": 0.0,
    "ee": 2.0,
    "e->w5": 2.0
  },
  "1": {
    "s": 24,
    "ss": 24,
    "t": 6,
    "c": 5,
    "ie": 0.0,
    "ee": 24.0,
    "e->w2": 9.0
  },
  "3": {
    "s": 2,
    "ss": 2,
    "t": 2,
    "c": 5,
    "ie": 0.0,
    "ee": 2.0,
    "e->w4": 2.0
  },
  "5": {
    "s": 2,
    "ss": 2,
    "t": 1,
    "c": 9,
    "ie": 2.0,
    "ee": 0.0,
    "e->w6": 0.0
  }
}